odoo/addons/base_multi_company/README.rst
odoo/addons/base_multi_company/__init__.py
odoo/addons/base_multi_company/__manifest__.py
odoo/addons/base_multi_company/hooks.py
odoo/addons/base_multi_company/i18n/base_multi_company.pot
odoo/addons/base_multi_company/i18n/es.po
odoo/addons/base_multi_company/i18n/fr.po
odoo/addons/base_multi_company/i18n/hr.po
odoo/addons/base_multi_company/i18n/nl_NL.po
odoo/addons/base_multi_company/i18n/pt.po
odoo/addons/base_multi_company/i18n/pt_BR.po
odoo/addons/base_multi_company/models/__init__.py
odoo/addons/base_multi_company/models/multi_company_abstract.py
odoo/addons/base_multi_company/models/res_company_assignment.py
odoo/addons/base_multi_company/security/ir.model.access.csv
odoo/addons/base_multi_company/static/description/icon.png
odoo/addons/base_multi_company/tests/__init__.py
odoo/addons/base_multi_company/tests/test_multi_company_abstract.py
odoo/addons/base_multi_company/tests/test_res_company_assignment.py
odoo11_addon_base_multi_company-11.0.1.0.0.99.dev9.dist-info/METADATA
odoo11_addon_base_multi_company-11.0.1.0.0.99.dev9.dist-info/RECORD
odoo11_addon_base_multi_company-11.0.1.0.0.99.dev9.dist-info/WHEEL
odoo11_addon_base_multi_company-11.0.1.0.0.99.dev9.dist-info/top_level.txt
